articles_to_anki/__init__.py
articles_to_anki/articles.py
articles_to_anki/cli.py
articles_to_anki/config.py
articles_to_anki/export_cards.py
articles_to_anki/fix_nltk.py
articles_to_anki/setup_app.py
articles_to_anki/text_utils.py
articles_to_anki-1.1.1.dist-info/licenses/LICENSE
articles_to_anki-1.1.1.dist-info/METADATA
articles_to_anki-1.1.1.dist-info/WHEEL
articles_to_anki-1.1.1.dist-info/entry_points.txt
articles_to_anki-1.1.1.dist-info/top_level.txt
articles_to_anki-1.1.1.dist-info/RECORD
